torchshow/__init__.py
torchshow/config.py
torchshow/flow.py
torchshow/torchshow.py
torchshow/utils.py
torchshow/visualization.py
torchshow-0.5.2.dist-info/licenses/LICENSE
torchshow-0.5.2.dist-info/METADATA
torchshow-0.5.2.dist-info/WHEEL
torchshow-0.5.2.dist-info/top_level.txt
torchshow-0.5.2.dist-info/RECORD
