Metadata-Version: 2.4
Name: torchshow
Version: 0.5.2
Summary: Visualizing PyTorch tensors with a single line of code.
Home-page: https://github.com/xwying/torchshow
Author: Xiaowen Ying
Author-email: shawnying.inbox@gmail.com
Classifier: Programming Language :: Python :: 3
Classifier: License :: OSI Approved :: MIT License
Classifier: Operating System :: OS Independent
Requires-Python: >=3.6
License-File: LICENSE
Requires-Dist: numpy
Requires-Dist: matplotlib
Dynamic: author
Dynamic: author-email
Dynamic: classifier
Dynamic: description
Dynamic: description-content-type
Dynamic: home-page
Dynamic: license-file
Dynamic: requires-dist
Dynamic: requires-python
Dynamic: summary
